LICENSE.txt
MANIFEST.in
README.md
setup.cfg
setup.py
djangocms_pathomation.egg-info/PKG-INFO
djangocms_pathomation.egg-info/SOURCES.txt
djangocms_pathomation.egg-info/dependency_links.txt
djangocms_pathomation.egg-info/requires.txt
djangocms_pathomation.egg-info/top_level.txt
pathomation/__init__.py
pathomation/admin.py
pathomation/apps.py
pathomation/cms_plugins.py
pathomation/forms.py
pathomation/models.py
pathomation/tests.py
pathomation/urls.py
pathomation/views.py
pathomation/migrations/__init__.py
pathomation/static/pathomation/images/pathomation.png
pathomation/static/static/test_connection.css
pathomation/static/static/test_connection.js
pathomation/templates/slides/_custom.html
pathomation/templates/slides/_slides.html
pathomation/templates/slides/elm-pep.js
pathomation/templates/slides/elm-pep.js.map
pathomation/templates/slides/file-saver.js
pathomation/templates/slides/file-saver.js.map
pathomation/templates/slides/font-awesome.css
pathomation/templates/slides/font-awesome.js
pathomation/templates/slides/font-awesome.js.map
pathomation/templates/slides/ieee754.js
pathomation/templates/slides/ieee754.js.map
pathomation/templates/slides/jquery.fancytree.css
pathomation/templates/slides/jquery.fancytree.js
pathomation/templates/slides/jquery.fancytree.js.map
pathomation/templates/slides/nouislider.css
pathomation/templates/slides/nouislider.js
pathomation/templates/slides/nouislider.js.map
pathomation/templates/slides/ol.css
pathomation/templates/slides/ol.js
pathomation/templates/slides/ol.js.map
pathomation/templates/slides/pbf.js
pathomation/templates/slides/pbf.js.map
pathomation/templates/slides/perfect-scrollbar.css
pathomation/templates/slides/perfect-scrollbar.js
pathomation/templates/slides/perfect-scrollbar.js.map
pathomation/templates/slides/pixelworks.js
pathomation/templates/slides/pixelworks.js.map
pathomation/templates/slides/pma.ui.css
pathomation/templates/slides/pma.ui.js
pathomation/templates/slides/pma.ui.js.map
pathomation/templates/slides/rbush.js
pathomation/templates/slides/rbush.js.map
pathomation/templates/slides/turf-jsts.js
pathomation/templates/slides/turf-jsts.js.map
pathomation/templates/slides/turf.js
pathomation/templates/slides/turf.js.map
