Metadata-Version: 2.1
Name: djangocms-pathomation
Version: 1.5.3
Summary: Add live slide viewing capabilities to your own website built on Django CMS
Home-page: https://www.pathomation.com/
Author: Pathomation
Author-email: info@pathomation.com
License: http://free.pathomation.com/eula/
Platform: UNKNOWN
Classifier: Environment :: Web Environment
Classifier: Operating System :: OS Independent
Classifier: Programming Language :: Python :: 3
Classifier: Programming Language :: Python :: 3.6
Classifier: Programming Language :: Python :: 3.7
Classifier: Programming Language :: Python :: 3.8
Requires-Python: >=3
